[
  {
    "slug": "3b4d8670-1c0c-43ad-9cce-c2bb5afd9de8",
    "stylesheet": "radial-gradient(circle at left, rgb(207, 135, 220), rgb(59, 104, 195))",
    "tags": [
      "standardcircle"
    ]
  },
  {
    "slug": "545cdcf9-6ab0-4fee-a37b-6bace74bcf25",
    "stylesheet": "radial-gradient(circle at center, rgb(192, 239, 210), rgb(47, 129, 239))",
    "tags": [
      "standardcircle"
    ]
  },
  {
    "slug": "3a1c80ce-4711-478a-88d8-99754a819af8",
    "stylesheet": "radial-gradient(circle at top, rgb(145, 186, 14), rgb(9, 119, 83))",
    "tags": [
      "standardcircle"
    ]
  },
  {
    "slug": "213fc058-fd9f-4bd5-ac16-d10d18166eaf",
    "stylesheet": "radial-gradient(circle at center, rgb(30, 108, 204), rgb(36, 61, 118))",
    "tags": [
      "standardcircle"
    ]
  },
  {
    "slug": "db405ace-b795-491f-b6cb-26fd83be0112",
    "stylesheet": "radial-gradient(circle at left, rgb(0, 46, 164), rgb(8, 121, 218))",
    "tags": [
      "standardcircle"
    ]
  },
  {
    "slug": "31e51492-b15a-46fa-a846-08e110878c00",
    "stylesheet": "radial-gradient(circle at right, rgb(202, 57, 146), rgb(11, 5, 110))",
    "tags": [
      "standardcircle"
    ]
  },
  {
    "slug": "401f85a4-499e-4896-8a68-fd33d3a82b7c",
    "stylesheet": "radial-gradient(circle at right, rgb(102, 218, 252), rgb(34, 111, 221))",
    "tags": [
      "standardcircle"
    ]
  },
  {
    "slug": "5f66348f-229a-4f69-9618-30a99b74dcf3",
    "stylesheet": "radial-gradient(circle at bottom, rgb(248, 160, 158), rgb(136, 31, 164))",
    "tags": [
      "standardcircle"
    ]
  },
  {
    "slug": "255b462d-32fb-47e0-b34d-c43f8b8fb0f9",
    "stylesheet": "radial-gradient(circle at right top, rgb(47, 245, 202), rgb(14, 125, 248))",
    "tags": [
      "standardcircle"
    ]
  },
  {
    "slug": "9aefdc8e-8845-48c7-a747-3bd904ef819f",
    "stylesheet": "radial-gradient(circle at center, rgb(93, 60, 152), rgb(10, 3, 9))",
    "tags": [
      "standardcircle"
    ]
  },
  {
    "slug": "c7481a83-1014-44e3-93ea-111439351220",
    "stylesheet": "radial-gradient(circle at right, rgb(138, 138, 138), rgb(251, 251, 251))",
    "tags": [
      "standardcircle"
    ]
  },
  {
    "slug": "75571217-2390-4f17-9569-98377cdfa900",
    "stylesheet": "radial-gradient(circle at center, rgb(252, 252, 252), rgb(82, 82, 82))",
    "tags": [
      "standardcircle"
    ]
  },
  {
    "slug": "44770536-9c9b-4d31-b549-19308719b9ca",
    "stylesheet": "radial-gradient(circle at center, rgb(71, 71, 71), rgb(8, 8, 8))",
    "tags": [
      "standardcircle",
      "darkbg"
    ]
  },
  {
    "slug": "893188f7-848a-4099-ac5a-c4bcc5597db8",
    "stylesheet": "radial-gradient(circle at center, rgb(252, 252, 252), rgb(129, 129, 129))",
    "tags": [
      "standardcircle"
    ]
  },
  {
    "slug": "d9cebd3b-8fb3-4a07-90bd-007bd115d1b2",
    "stylesheet": "radial-gradient(circle at center, rgb(249, 249, 249), rgb(167, 167, 167))",
    "tags": [
      "standardcircle"
    ]
  },
  {
    "slug": "b1cc9dc5-a656-4c75-b8a8-8db7629d100f",
    "stylesheet": "radial-gradient(circle at center, rgb(238, 238, 238), rgb(167, 167, 167))",
    "tags": [
      "standardcircle"
    ]
  },
  {
    "slug": "4461bc66-2a26-4534-8198-31c95b38b8e5",
    "stylesheet": "radial-gradient(circle at right top, rgb(121, 121, 121), rgb(246, 246, 246))",
    "tags": [
      "standardcircle"
    ]
  },
  {
    "slug": "791b5b2a-63f0-482f-badf-40047846c174",
    "stylesheet": "radial-gradient(circle at left bottom, rgb(150, 150, 150), rgb(249, 249, 249))",
    "tags": [
      "standardcircle"
    ]
  },
  {
    "slug": "588c5e01-85c5-496e-8ff4-7a5e4d6c0be5",
    "stylesheet": "radial-gradient(circle at bottom, rgb(229, 229, 229), rgb(109, 109, 109))",
    "tags": [
      "standardcircle"
    ]
  },
  {
    "slug": "bcd6e3ff-c296-4644-adf5-7e0b85382b47",
    "stylesheet": "radial-gradient(circle at top, rgb(243, 243, 243), rgb(133, 133, 133))",
    "tags": [
      "standardcircle"
    ]
  },
  {
    "slug": "4f638013-6fdb-4f2c-9ee4-66a689690500",
    "stylesheet": "radial-gradient(circle at right bottom, rgb(46, 243, 212), rgb(80, 17, 213), rgb(63, 130, 213))",
    "tags": [
      "standardcircle"
    ]
  },
  {
    "slug": "17af3798-c702-4fcf-b574-59c6efc3ba8d",
    "stylesheet": "radial-gradient(circle at bottom, rgb(254, 195, 95), rgb(233, 119, 44), rgb(244, 157, 70))",
    "tags": [
      "standardcircle"
    ]
  },
  {
    "slug": "60304c77-6207-410f-8c99-b8a4fde43bce",
    "stylesheet": "radial-gradient(circle at top, rgb(243, 177, 46), rgb(230, 153, 36), rgb(217, 129, 26), rgb(204, 104, 15), rgb(191, 80, 5))",
    "tags": [
      "standardcircle"
    ]
  },
  {
    "slug": "1f3cca48-2ac8-44d1-b501-a1a9d6076503",
    "stylesheet": "radial-gradient(circle at top, rgb(244, 234, 104), rgb(234, 179, 103), rgb(224, 125, 103), rgb(214, 70, 102), rgb(204, 15, 101))",
    "tags": [
      "standardcircle"
    ]
  },
  {
    "slug": "b1bd400a-9dfa-48d8-81de-8e45ac357178",
    "stylesheet": "radial-gradient(circle at top, rgb(235, 41, 254), rgb(185, 42, 217), rgb(134, 42, 180), rgb(84, 43, 142), rgb(33, 43, 105))",
    "tags": [
      "standardcircle"
    ]
  },
  {
    "slug": "975a8afa-bbcf-4547-a780-03c6c0dc34cd",
    "stylesheet": "radial-gradient(circle at center, rgb(10, 133, 202), rgb(23, 106, 192), rgb(35, 79, 183), rgb(48, 51, 173), rgb(60, 24, 163))",
    "tags": [
      "standardcircle"
    ]
  },
  {
    "slug": "0d571651-1e36-467f-81c6-96e69e9222cf",
    "stylesheet": "radial-gradient(circle at center, rgb(215, 105, 155), rgb(187, 82, 146), rgb(158, 59, 136), rgb(130, 35, 127), rgb(101, 12, 117))",
    "tags": [
      "standardcircle"
    ]
  },
  {
    "slug": "24ccb24e-8ec7-4972-b184-ca333bcbc2ad",
    "stylesheet": "radial-gradient(circle at center, rgb(86, 197, 113), rgb(77, 181, 95), rgb(67, 165, 77), rgb(58, 149, 59), rgb(48, 133, 41))",
    "tags": [
      "standardcircle"
    ]
  },
  {
    "slug": "6623a2f7-6a59-4009-93b1-4e70e82e8421",
    "stylesheet": "radial-gradient(circle at center, rgb(69, 48, 242), rgb(63, 48, 184), rgb(56, 48, 125), rgb(50, 47, 67), rgb(43, 47, 8))",
    "tags": [
      "standardcircle"
    ]
  },
  {
    "slug": "830c0d53-aae2-4e58-9586-92486aa01560",
    "stylesheet": "radial-gradient(circle at center, rgb(80, 32, 84), rgb(62, 35, 81), rgb(44, 38, 79), rgb(26, 40, 76), rgb(8, 43, 73))",
    "tags": [
      "standardcircle"
    ]
  },
  {
    "slug": "7d369243-a2f0-4e86-b420-2dd3276ff49d",
    "stylesheet": "radial-gradient(circle at center, rgb(241, 195, 19), rgb(244, 150, 32), rgb(246, 105, 45), rgb(249, 59, 57), rgb(251, 14, 70))",
    "tags": [
      "standardcircle"
    ]
  },
  {
    "slug": "1f332d20-d77f-48e5-aa8b-e1eb7f4b3ba0",
    "stylesheet": "radial-gradient(circle at center, rgb(15, 78, 199), rgb(21, 67, 172), rgb(27, 56, 145), rgb(33, 44, 118), rgb(39, 33, 91))",
    "tags": [
      "standardcircle"
    ]
  },
  {
    "slug": "5b9e57df-17a4-4280-8394-86178d63be75",
    "stylesheet": "radial-gradient(circle at center, rgb(233, 255, 32), rgb(176, 209, 39), rgb(118, 163, 47), rgb(61, 116, 54), rgb(3, 70, 61))",
    "tags": [
      "standardcircle"
    ]
  },
  {
    "slug": "00e7a7e2-560d-4b5c-8e11-1554453d6139",
    "stylesheet": "radial-gradient(circle at center, rgb(191, 240, 234), rgb(149, 214, 228), rgb(107, 188, 223), rgb(65, 162, 217), rgb(23, 136, 211))",
    "tags": [
      "standardcircle"
    ]
  },
  {
    "slug": "c00ccd93-ae86-421f-b0d7-81ad338c5cac",
    "stylesheet": "radial-gradient(circle at center, rgb(226, 254, 178), rgb(180, 230, 146), rgb(134, 206, 115), rgb(87, 182, 83), rgb(41, 158, 51))",
    "tags": [
      "standardcircle"
    ]
  },
  {
    "slug": "1c2980f2-3e94-4f25-85ac-067e99adce92",
    "stylesheet": "radial-gradient(circle at center, rgb(252, 155, 156), rgb(237, 122, 126), rgb(221, 89, 96), rgb(206, 56, 65), rgb(190, 23, 35))",
    "tags": [
      "standardcircle"
    ]
  },
  {
    "slug": "17c4548a-8cc4-4251-9a81-eb39058b2cff",
    "stylesheet": "radial-gradient(circle at right, rgb(240, 101, 23), rgb(242, 194, 28))",
    "tags": [
      "standardcircle"
    ]
  },
  {
    "slug": "a606686d-a01a-4043-b4c1-811c3f158831",
    "stylesheet": "radial-gradient(circle at center, rgb(233, 240, 92), rgb(236, 129, 32))",
    "tags": [
      "standardcircle"
    ]
  },
  {
    "slug": "67834fa1-5981-4172-b685-0d48093c7285",
    "stylesheet": "radial-gradient(circle at center, rgb(225, 137, 68), rgb(101, 40, 15))",
    "tags": [
      "standardcircle"
    ]
  },
  {
    "slug": "6906eccb-fb52-4641-96be-9f748bb6f948",
    "stylesheet": "radial-gradient(circle at top, rgb(255, 13, 187), rgb(115, 55, 110))",
    "tags": [
      "standardcircle"
    ]
  },
  {
    "slug": "59b53858-38cb-49f5-b75f-173945018b6f",
    "stylesheet": "radial-gradient(circle at center, rgb(6, 242, 198), rgb(12, 102, 197))",
    "tags": [
      "standardcircle"
    ]
  },
  {
    "slug": "f3ebe8cc-1cba-4db6-9175-2617de39378c",
    "stylesheet": "radial-gradient(circle at left top, rgb(253, 225, 94), rgb(113, 193, 12))",
    "tags": [
      "standardcircle"
    ]
  },
  {
    "slug": "1ad7b2c4-57e9-4f13-9387-85c776afa8c3",
    "stylesheet": "radial-gradient(circle at right top, rgb(221, 154, 33), rgb(210, 55, 33))",
    "tags": [
      "standardcircle"
    ]
  },
  {
    "slug": "0721f5a7-a9f3-4d00-a8e3-5a972d48b8a9",
    "stylesheet": "radial-gradient(circle at top, rgb(230, 217, 186), rgb(12, 92, 185))",
    "tags": [
      "standardcircle"
    ]
  },
  {
    "slug": "48c8f3e8-7724-4133-88dc-1637f7b3e46d",
    "stylesheet": "radial-gradient(circle at bottom, rgb(30, 227, 217), rgb(4, 89, 247))",
    "tags": [
      "standardcircle"
    ]
  },
  {
    "slug": "9d824518-276b-41d6-bf88-f034116e5188",
    "stylesheet": "radial-gradient(circle at top, rgb(38, 217, 249), rgb(46, 14, 92))",
    "tags": [
      "standardcircle"
    ]
  },
  {
    "slug": "9a4b929f-b33e-47ec-985c-aa6a00ba9d22",
    "stylesheet": "radial-gradient(circle at bottom, rgb(216, 248, 247), rgb(253, 176, 22))",
    "tags": [
      "standardcircle"
    ]
  },
  {
    "slug": "2e9c6782-5d42-4c9e-88d2-34068607ad22",
    "stylesheet": "radial-gradient(circle at bottom, rgb(95, 30, 254), rgb(66, 32, 127))",
    "tags": [
      "standardcircle"
    ]
  },
  {
    "slug": "04e490ef-f02e-446f-a41e-14e51424e7e0",
    "stylesheet": "radial-gradient(circle at top, rgb(213, 140, 216), rgb(74, 39, 191))",
    "tags": [
      "standardcircle"
    ]
  },
  {
    "slug": "57d2dd00-e4d6-44ab-b618-8307778018ae",
    "stylesheet": "radial-gradient(circle at bottom, rgb(176, 142, 252), rgb(60, 0, 159))",
    "tags": [
      "standardcircle"
    ]
  },
  {
    "slug": "4a0a00da-f08c-4516-97a1-03a311a7dd7e",
    "stylesheet": "radial-gradient(circle at center, rgb(15, 173, 158), rgb(36, 59, 244))",
    "tags": [
      "standardcircle"
    ]
  },
  {
    "slug": "3b2fc62d-e7d1-4f16-b368-9c3fcae5b124",
    "stylesheet": "radial-gradient(circle at center, rgb(234, 238, 79), rgb(250, 124, 72))",
    "tags": [
      "standardcircle"
    ]
  },
  {
    "slug": "ca391474-81d6-4019-8b86-02fce3af1367",
    "stylesheet": "radial-gradient(circle at center, rgb(127, 62, 211), rgb(0, 23, 70))",
    "tags": [
      "standardcircle"
    ]
  },
  {
    "slug": "ee74bced-99fd-41b3-9956-552e43550c79",
    "stylesheet": "radial-gradient(circle at center, rgb(213, 109, 39), rgb(29, 16, 5))",
    "tags": [
      "standardcircle"
    ]
  },
  {
    "slug": "8c795b7e-be03-40fa-8395-39011f2bc8c3",
    "stylesheet": "radial-gradient(circle at right, rgb(204, 90, 255), rgb(30, 8, 124))",
    "tags": [
      "standardcircle"
    ]
  },
  {
    "slug": "9b27d1b4-e891-4e9c-a170-75906d5e2218",
    "stylesheet": "radial-gradient(circle at top, rgb(255, 255, 34), rgb(8, 130, 133))",
    "tags": [
      "standardcircle"
    ]
  },
  {
    "slug": "a3a9f7df-9323-41c9-9499-676d07a3f652",
    "stylesheet": "radial-gradient(circle at center, rgb(220, 196, 33), rgb(98, 196, 96))",
    "tags": [
      "standardcircle"
    ]
  },
  {
    "slug": "7eaeb5f6-3f5f-49c1-bf37-1bb6be769a88",
    "stylesheet": "radial-gradient(circle at right, rgb(6, 204, 208), rgb(29, 101, 238))",
    "tags": [
      "standardcircle"
    ]
  },
  {
    "slug": "2b10064c-9f14-48f0-b51f-28a390817049",
    "stylesheet": "radial-gradient(circle at top, rgb(203, 6, 229), rgb(9, 123, 207))",
    "tags": [
      "standardcircle"
    ]
  },
  {
    "slug": "01ca54d8-b2b0-4d99-a605-d2da2eff0fa6",
    "stylesheet": "radial-gradient(circle at bottom, rgb(87, 232, 245), rgb(42, 114, 213))",
    "tags": [
      "standardcircle"
    ]
  },
  {
    "slug": "700d0330-5d93-45ae-824e-257cfcf3d643",
    "stylesheet": "radial-gradient(circle at bottom, rgb(141, 118, 197), rgb(119, 60, 147))",
    "tags": [
      "standardcircle"
    ]
  },
  {
    "slug": "d8427bb9-610a-48a5-8f15-8308704aabd0",
    "stylesheet": "radial-gradient(circle at bottom, rgb(84, 13, 239), rgb(79, 34, 84))",
    "tags": [
      "standardcircle"
    ]
  }
]